.tmuxp.yaml
CHANGES
LICENSE
MANIFEST.in
README.rst
__about__.py
setup.py
cihaidata_unihan.egg-info/PKG-INFO
cihaidata_unihan.egg-info/SOURCES.txt
cihaidata_unihan.egg-info/dependency_links.txt
cihaidata_unihan.egg-info/entry_points.txt
cihaidata_unihan.egg-info/not-zip-safe
cihaidata_unihan.egg-info/top_level.txt
doc/api.rst
doc/cli.rst
doc/history.rst
doc/index.rst
doc/spec.rst
requirements/base.txt
requirements/dev.txt
requirements/doc.txt
requirements/test.txt