Metadata-Version: 1.1
Name: cihaidata-unihan
Version: 0.4.1
Summary: Tool to build UNIHAN dataset into datapackage / simple data format.
Home-page: https://cihaidata-unihan.git-pull.com
Author: Tony Narlock
Author-email: cihai@git-pull.com
License: MIT
Download-URL: https://pypi.python.org/pypi/cihaidata-unihan
Keywords: cihaidata-unihan
Platform: UNKNOWN
Classifier: Development Status :: 3 - Alpha
Classifier: License :: OSI Approved :: MIT License
Classifier: Environment :: Web Environment
Classifier: Intended Audience :: Developers
Classifier: Programming Language :: Python
Classifier: Programming Language :: Python :: 2.7
Classifier: Programming Language :: Python :: 3
Classifier: Programming Language :: Python :: 3.3
Classifier: Programming Language :: Python :: 3.4
Classifier: Programming Language :: Python :: 3.5
Classifier: Programming Language :: Python :: 3.6
Classifier: Programming Language :: Python :: Implementation :: PyPy
Classifier: Topic :: Utilities
